pytoolib/__init__.py
pytoolib/primary.py
pytoolib/aws/__init__.py
pytoolib/aws/dynamodb.py
python_tool_library-0.0.1.dist-info/LICENSE
python_tool_library-0.0.1.dist-info/METADATA
python_tool_library-0.0.1.dist-info/WHEEL
python_tool_library-0.0.1.dist-info/top_level.txt
python_tool_library-0.0.1.dist-info/RECORD
